suvi/__init__.py
suvi/app.py
suvi/app_state.py
suvi/config_cache.py
suvi/multiuser_basic_auth.py
suvi/task.py
suvi/static/site.css
suvi/static/dependencies/bootstrap.bundle.js
suvi/static/dependencies/bootstrap.bundle.min.js
suvi/static/dependencies/bootstrap.min.css
suvi/static/dependencies/htmx.min.js
suvi/static/dependencies/jquery.min.js
suvi/static/img/code.svg
suvi/static/img/ecmind-logo-dark.svg
suvi/static/img/ecmind-logo-light.svg
suvi/static/img/info.svg
suvi/static/img/log.svg
suvi/static/img/recycle.svg
suvi/static/img/reload.svg
suvi/static/img/remove.svg
suvi/static/img/shutdown.svg
suvi/static/img/start.svg
suvi/static/img/stop.png
suvi/static/img/stop.svg
suvi/static/img/suvi-dark.svg
suvi/static/img/suvi-light.svg
suvi/static/img/text.svg
suvi/static/img/exec/shell.svg
suvi/static/img/exec/stop.svg
suvi/static/img/exec/system.svg
suvi/static/img/exec/talend.svg
suvi/templates/about.html
suvi/templates/base.html
suvi/templates/log.html
suvi/templates/log_inner.html
suvi/templates/manage.html
suvi/templates/nav.html
suvi/templates/osslic.html
suvi/templates/ps.html
suvi/templates/ps_inner.html
suvi/templates/taskinfo.html
suvi/templates/tasklog.html
suvi/templates/tasklog_inner.html
suvi/templates/tasklogs.html
suvi/templates/tasklogs_inner.html
suvi/templates/tasks.html
suvi/templates/tasks_inner.html
suvi-2.7.8.dist-info/LICENSE
suvi-2.7.8.dist-info/METADATA
suvi-2.7.8.dist-info/WHEEL
suvi-2.7.8.dist-info/entry_points.txt
suvi-2.7.8.dist-info/top_level.txt
suvi-2.7.8.dist-info/RECORD
