Metadata-Version: 2.1
Name: suvi
Version: 2.7.8
Summary: ECMind Supervisor
Author-email: ECMind GmbH <info@ecmind.ch>
License: GNU GENERAL PUBLIC LICENSE
Project-URL: Homepage, https://ecmind.ch/products/suvi/
Project-URL: Documentation, https://gitlab.ecmind.ch/open/suvi/-/wikis/home
Project-URL: Repository, https://gitlab.ecmind.ch/open/suvi.git
Project-URL: Issues, https://ecm.community/c/suvi/
Project-URL: Changelog, https://gitlab.ecmind.ch/open/suvi/-/raw/main/CHANGELOG
Classifier: Programming Language :: Python :: 3.11
Classifier: Operating System :: OS Independent
Requires-Python: >=3.11
License-File: LICENSE
Requires-Dist: flask
Requires-Dist: markdown
Requires-Dist: Flask-BasicAuth
Requires-Dist: waitress
Requires-Dist: psutil
Requires-Dist: requests
Requires-Dist: uptime
Requires-Dist: typer
Provides-Extra: dev
Requires-Dist: setuptools-scm; extra == "dev"
Requires-Dist: wheel; extra == "dev"
Requires-Dist: black; extra == "dev"
Requires-Dist: twine; extra == "dev"
Requires-Dist: build; extra == "dev"
